pyrelatics2/__init__.py
pyrelatics2/client.py
pyrelatics2/exceptions.py
pyrelatics2/result_classes.py
pyrelatics2/utils.py
pyrelatics2/version.py
pyrelatics2-0.3.2.dist-info/licenses/LICENSE
pyrelatics2-0.3.2.dist-info/METADATA
pyrelatics2-0.3.2.dist-info/WHEEL
pyrelatics2-0.3.2.dist-info/top_level.txt
pyrelatics2-0.3.2.dist-info/RECORD
