Metadata-Version: 2.4
Name: pyrelatics2
Version: 0.3.2
Summary: Python package to interact with Relatics webservices
Author-email: Rense Klinkenberg <r@klinkenberg.ws>
License: Apache-2.0
Project-URL: Homepage, https://github.com/rense-k/pyrelatics2
Project-URL: Repository, https://github.com/rense-k/pyrelatics2.git
Project-URL: Issues, https://github.com/rense-k/pyrelatics2/issues
Project-URL: Changelog, https://github.com/rense-k/pyrelatics2/blob/dev/CHANGELOG.md
Keywords: Relatics,Relatics v5,webservice,soap-client,oauth2
Classifier: Development Status :: 4 - Beta
Classifier: Intended Audience :: Developers
Classifier: License :: OSI Approved :: Apache Software License
Classifier: Natural Language :: English
Classifier: Operating System :: OS Independent
Classifier: Programming Language :: Python
Classifier: Programming Language :: Python :: 3 :: Only
Classifier: Programming Language :: Python :: 3.10
Classifier: Programming Language :: Python :: 3.11
Classifier: Programming Language :: Python :: 3.12
Classifier: Programming Language :: Python :: 3.13
Classifier: Programming Language :: Python :: 3.14
Classifier: Topic :: Internet
Classifier: Topic :: Software Development :: Libraries
Requires-Python: >=3.10
License-File: LICENSE
Requires-Dist: suds-community<1.3.0,>=1.1.2
Requires-Dist: colorama
Provides-Extra: dev
Requires-Dist: black; extra == "dev"
Requires-Dist: isort; extra == "dev"
Requires-Dist: pylint; extra == "dev"
Requires-Dist: wheel; extra == "dev"
Requires-Dist: twine; extra == "dev"
Provides-Extra: test
Requires-Dist: parameterized; extra == "test"
Dynamic: license-file
